resources/openapi.json
rs_server_frontend/__init__.py
rs_server_frontend/main.py
rs_server_frontend-99.99.dist-info/METADATA
rs_server_frontend-99.99.dist-info/WHEEL
rs_server_frontend-99.99.dist-info/RECORD
